cryptii/__init__.py
cryptii-0.0.2.dist-info/METADATA
cryptii-0.0.2.dist-info/WHEEL
cryptii-0.0.2.dist-info/top_level.txt
cryptii-0.0.2.dist-info/RECORD
